Workbook

Sheet README
A1: CUDA C++ Projects for Health, Medicine & the Life Sciences
A2: Sortable catalog of 301 GPU-accelerated project ideas across 14 domains.
A4: How to use this workbook
A5: • The "Projects" tab has one row per project. Click any column header's filter arrow to sort or filter (e.g., sort by Difficulty, or filter Domain = "Genomics").
A6: • Columns: Domain, ID, Project, Difficulty, Maturity, Deep Dive, Key Algorithms, Datasets, Starter Repos/Tools, and CUDA Libraries & GPU Pattern.
A7: • The "By Domain" tab summarizes counts per domain and difficulty/maturity (live formulas).
A8: • A companion Markdown file (CUDA_CPP_Healthcare_Projects_DeepDive.md) has the same content in long-form reading format.
A10: Legend
A11: Difficulty: 🟢 Beginner-friendly · 🟡 Intermediate · 🔴 Advanced
A12: Maturity: Established (mature tooling) · Active R&D (research-grade) · Frontier/Theoretical (open problems; the GPU formulation itself is a contribution)
A14: Note on links
A15: Dataset and repository URLs were verified during research, but the field moves quickly — a few may have moved. Items marked "(verify URL)" were flagged as needing a quick confirmation. Always check the latest project page.
... A18: This is an educational catalog of project ideas. Any clinical, diagnostic, or therapeutic application requires appropriate validation, regulatory review, and expert oversight.

Sheet Projects
A1: # | B1: Section | C1: Domain | D1: ID | E1: Project | F1: Difficulty | G1: Maturity | H1: Deep Dive | I1: Key Algorithms | J1: Datasets | K1: Starter Repos / Tools | L1: CUDA Libraries & GPU Pattern
A2: 1 | B2: 1 | C2: Drug Discovery & Molecular Design | D2: 1.1 | E2: Molecular Dynamics Engine | F2: Beginner | G2: Established | H2: Classical MD simulates the time evolution of every atom in a biomolecular system by integrating Newton's equations of motion using empirical force fields (AMBER, CHARMM, GROMOS). Each timestep requires evaluating bonded interactions (bonds, angles, dihedrals) and non-bonded interactions (Lennard-Jones + electrostatics) for millions of atom pairs. GPUs accelerate the embarrassingly parallel pairwise force evaluation, reducing a day of CPU work to minutes on modern A100-class cards. The critical bottleneck — neighbor-list construction and PME reciprocal-space summation — maps cleanly onto CUDA threadblocks. Multi-GPU scaling via domain decomposition allows systems of 10–100 million atoms to be simulated in production. | I2: Verlet/leapfrog integrator, LINCS/SHAKE bond constraint solvers, Particle-Mesh Ewald (PME) electrostatics, Lennard-Jones cutoff with long-range dispersion correction, Berendsen/Parrinello-Rahman barostat, velocity rescaling/Nosé-Hoover thermostat. | J2: CHARMM36m force-field parameter set — comprehensive parameters for proteins, lipids, nucleic acids and carbohydrates (https://mackerell.umaryland.edu/charmm_ff.shtml); AMBER ff19SB — protein force field with improved backbone torsion potentials (https://ambermd.org); GPCRmd database — curated MD trajectories of GPCR proteins (https://gpcrmd.org); MoDEL — molecular dynamics extended library of protein simulations (https://mmb.irbbarcelona.org/MoDEL/). | K2: GROMACS (https://github.com/gromacs/gromacs) — production-grade GPU-accelerated MD engine with CUDA/HIP/SYCL backends; OpenMM (https://github.com/openmm/openmm) — Python-scriptable MD toolkit with CUDA, OpenCL, and CPU platforms; NAMD (https://www.ks.uiuc.edu/Research/namd/) — scalable MD with multi-GPU support via CUDA; AMBER pmemd.cuda (https://ambermd.org/GPUSupport.php) — highly optimized GPU MD engine for AMBER force fields. | L2: cuFFT for PME reciprocal sum, custom CUDA kernels for pairwise force evaluation, thrust for sorted neighbor list, NCCL for multi-GPU halo exchange; pattern is data-parallel threadblocks over atom pairs with shared-memory reductions. --
A3: 2 | B3: 1 | C3: Drug Discovery & Molecular Design | D3: 1.2 | E3: Particle-Mesh Ewald Electrostatics | F3: Beginner | G3: Established | H3: Long-range electrostatics in periodic MD systems cannot be truncated without severe artifacts; PME splits the Coulomb sum into a short-range real-space part (evaluated with cutoff) and a smooth long-range reciprocal-space part evaluated on a 3D grid via FFT. The GPU acceleration opportunity is two-fold: the charge spreading (particle-to-mesh) and force interpolation (mesh-to-particle) steps are data-parallel over atoms, while the 3D FFT is handled by cuFFT. PME scales as O(N log N) and dominates walltime for large biological systems. Achieving double-precision accuracy at float throughput is the main engineering challenge. | I3: Ewald summation, B-spline charge interpolation (order 4–6), 3D FFT on GPU, real-space erfc damping, smooth PME (SPME), Particle-Particle Particle-Mesh (P3M). | J3: CHARMM-GUI solvation benchmark sets — pre-built periodic protein-water boxes (https://charmm-gui.org); D. E. Shaw Research Anton trajectories — ms-scale trajectory archives (available via DE Shaw); ion channel benchmark systems (MemProtMD, https://memprotmd.bioch.ox.ac.uk). | K3: GROMACS CUDA PME (https://github.com/gromacs/gromacs) — reference GPU PME implementation; NAMD GPU PME (https://www.ks.uiuc.edu/Research/namd/) — tiled domain-decomposed PME; OpenMM PME plugin (https://github.com/openmm/openmm) — Python-accessible PME with mixed-precision; cuFFT (https://developer.nvidia.com/cufft) — NVIDIA's FFT library used internally by all above. | L3: cuFFT for 3D FFT; custom CUDA kernels for B-spline charge spreading (atom-parallel) and gradient interpolation; shared-memory tiling to minimize global memory traffic; atomics for scatter-add accumulation on the charge grid. --
A4: 3 | B4: 1 | C4: Drug Discovery & Molecular Design | D4: 1.3 | E4: Molecular Docking Engine | F4: Beginner | G4: Established | H4: Molecular docking predicts the preferred binding pose and score of a small molecule within a protein binding pocket by sampling ligand conformations (translations, rotations, torsions) and scoring each with an empirical or knowledge-based energy function. The scoring function evaluation for each sampled pose is independent, creating massive data parallelism — thousands of poses per ligand, millions of ligands per campaign. AutoDock-GPU achieves >1000× speedup over single-CPU AutoDock4 by running the Lamarckian genetic algorithm (LGA) in parallel across GPU threads, each evaluating a distinct pose. The bottleneck is the grid-based force-field energy lookup, which benefits from GPU texture-cache acceleration. | I4: Lamarckian Genetic Algorithm (LGA), gradient-based local search (BFGS), grid-based energy evaluation (electrostatics + vdW precalculated on 3D grids), scoring functions (AutoDock4, Vina, Vinardo, AD4). | J4: DUD-E — directory of useful decoys enhanced, 102 targets with actives and decoys (https://dude.docking.org); ChEMBL — bioactivity database with >2M compounds (https://www.ebi.ac.uk/chembl/); PDB-bind — curated protein-ligand complexes with binding affinities (http://www.pdbbind.org.cn); CASF benchmark — comparative assessment of scoring functions (http://www.pdbbind.org.cn/casf.php). | K4: AutoDock-GPU (https://github.com/ccsb-scripps/AutoDock-GPU) — CUDA/OpenCL GPU docking with LGA parallelism; Uni-Dock (https://github.com/dptech-corp/Uni-Dock) — GPU-accelerated batch docking with >2000× speedup on V100; GNINA (https://github.com/gnina/gnina) — CNN-scored docking fork of smina; Vina-GPU 2.1 (https://github.com/DeltaGroupNJUPT/Vina-GPU-2.1) — GPU-accelerated AutoDock Vina with RILC-BFGS. | L4: Texture memory for 3D grid lookups, CUDA threadblocks each running one GA individual per ligand, warp-level reduction for fitness evaluation; grid-strided loops for pose batch processing. --
A5: 4 | B5: 1 | C5: Drug Discovery & Molecular Design | D5: 1.4 | E5: Ultra-Large Virtual Screening | F5: Beginner | G5: Established | H5: Modern make-on-demand chemical libraries (Enamine REAL: >6 billion compounds, ZINC: ~2 billion) make exhaustive docking computationally prohibitive with CPU resources. GPU-accelerated docking allows screening of billions of compounds by batching thousands of ligands simultaneously on a single GPU. Additionally, ML surrogate models trained on docked subsets (active learning / Bayesian optimization) dramatically reduce the number of full docking evaluations required. Specialized tools like HASTEN and REINVENT combine GPU docking with ML to achieve 90% recall of true top-1000 hits after evaluating only 1% of the library. The Summit supercomputer campaign against COVID-19 targets docked >1 billion compounds using AutoDock-GPU. | I5: GPU-batched LGA/BFGS docking, Bayesian active learning, surrogate-model filtering (random forest, GNN), pharmacophore pre-filtering, shape screening pre-filter, Lipinski/ADMET filter cascades. | J5: Enamine REAL library — >6B synthesizable compounds (https://enamine.net/compound-collections/real-compounds); ZINC20 — free virtual screening database (https://zinc20.docking.org); ChEMBL — bioactivity reference (https://www.ebi.ac.uk/chembl/); ExCAPE-DB — large-scale public chemogenomics dataset (https://solr.ideaconsult.net/search/excape/). | K5: AutoDock-GPU (https://github.com/ccsb-scripps/AutoDock-GPU) — core CUDA docking engine used in billion-compound campaigns; Uni-Dock (https://github.com/dptech-corp/Uni-Dock) — high-throughput GPU docking with batch input; DiffDock (https://github.com/gcorso/DiffDock) — diffusion model for blind docking of large libraries; gpusimilarity (https://github.com/schrodinger/gpusimilarity) — GPU fingerprint similarity for rapid pre-screening. | L5: Texture memory for grid lookups; warp-parallel GA evaluation; multiple ligands co-resident in GPU memory; NVLink multi-GPU for campaign-scale throughput; thrust for top-K selection. --
A6: 5 | B6: 1 | C6: Drug Discovery & Molecular Design | D6: 1.5 | E6: Free Energy Perturbation / Thermodynamic Integration | F6: Beginner | G6: Established | H6: FEP and TI compute binding free energy differences (ΔΔG) between two ligands by running MD along an alchemical λ-pathway that slowly transforms one molecule into another. Each λ-window requires independent GPU MD trajectories; the collection of windows is trivially parallel across GPUs. The critical computational cost is the length and number of λ-windows required for convergence (typically 12–24 windows × 2–5 ns each). GPU-accelerated pmemd.cuda and NAMD-FEP achieve >10× speedup over CPU, reducing multi-day calculations to hours on a single A100. Relative FEP (RBFE) is now a standard tool in lead optimization pipelines at major pharmaceutical companies. | I6: Alchemical λ-coupling, soft-core potentials (Beutler/Zacharias), multi-state Bennett acceptance ratio (MBAR), thermodynamic integration quadrature, replica exchange with solute tempering (REST2), overlap matrix assessment. | J6: Merck FEP benchmark set — 8 targets with experimental ΔΔG (available via OpenFE; https://github.com/OpenFreeEnergy/openfe); FEP+ validation set (Schrodinger, verify URL); PDB-bind — experimental binding affinities (http://www.pdbbind.org.cn); ChEMBL activity data for target families (https://www.ebi.ac.uk/chembl/). | K6: OpenFE (https://github.com/OpenFreeEnergy/openfe) — open FEP toolkit supporting GROMACS and OpenMM backends; GROMACS FEP (https://github.com/gromacs/gromacs) — GPU-accelerated FEP with MBAR post-processing via alchemlyb; OpenMMTools (https://github.com/choderalab/openmmtools) — alchemical replica exchange on GPU via OpenMM; AMBER pmemd.cuda TI (https://ambermd.org/GPUSupport.php) — softcore TI on NVIDIA GPUs. | L6: Full MD engine on GPU (cuFFT PME + custom force kernels); embarrassingly parallel λ-window array across multiple GPUs; NCCL for REMD communication; CPU post-processing via alchemlyb/MBAR. --
A7: 6 | B7: 1 | C7: Drug Discovery & Molecular Design | D7: 1.6 | E7: Enhanced Sampling — Metadynamics & Replica Exchange | F7: Beginner | G7: Established | H7: Standard MD cannot cross large free energy barriers on accessible timescales. Enhanced sampling methods accelerate conformational exploration by adding history-dependent bias potentials (metadynamics) or by running multiple copies at different temperatures/Hamiltonians (REMD/HREX). PLUMED plugs into GROMACS, NAMD, OpenMM, and LAMMPS to implement CVs and bias on the fly. GPU MD trajectories feed the bias engine with minimal overhead. Well-tempered metadynamics ensures convergence of the free energy surface (FES) and is widely used for drug binding pathway elucidation. GPU-MetaD (2025) achieves full-lifecycle GPU acceleration for ML potential metadynamics with systems up to 1.3M atoms. | I7: Well-tempered metadynamics, funnel metadynamics, Hamiltonian replica exchange (HREX), temperature REMD (T-REMD), replica exchange with solute tempering (REST2), collective variable (CV) on-the-fly evaluation, free energy surface estimation via reweighting. | J7: PLUMED-NEST — repository of published metadynamics/enhanced sampling input files (https://www.plumed-nest.org); GPCRmd trajectory archive (https://gpcrmd.org); D. E. Shaw millisecond MD datasets (available via RCSB); benchmark FES for alanine dipeptide / chignolin (commonly used test systems). | K7: PLUMED (https://github.com/plumed/plumed2) — plugin for collective variables and enhanced sampling, GPU-compatible via host MD engine; GROMACS + PLUMED (https://github.com/gromacs/gromacs) — standard GPU metadynamics stack; OpenPathSampling (https://github.com/openpathsampling/openpathsampling) — transition path sampling framework; HTMD (https://github.com/Acellera/htmd) — high-throughput MD with adaptive sampling on GPU clusters. | L7: Bias potential evaluation on CPU via PLUMED with negligible overhead; full MD force/integration on GPU; multi-walker metadynamics uses MPI + NCCL across GPUs; GPU kernels for on-the-fly CV computation in GPU-MetaD. --
A8: 7 | B8: 1 | C8: Drug Discovery & Molecular Design | D8: 1.7 | E8: Quantum Chemistry / DFT | F8: Beginner | G8: Established | H8: Density Functional Theory (DFT) calculates electronic structure by solving the Kohn-Sham equations self-consistently on a basis set (plane waves or Gaussians). The dominant cost is the construction of the Fock/Kohn-Sham matrix via electron repulsion integrals (ERIs) — an O(N^4) bottleneck that GPUs reduce substantially by computing integrals in batches. TeraChem pioneered GPU-accelerated DFT and can achieve 100× speedup over single-CPU codes. Applications in drug discovery include geometry optimization of drug fragments, calculation of electrostatic potential maps for pharmacophore generation, and QM-derived force field parameterization. | I8: Kohn-Sham SCF, B3LYP/ωB97X-D exchange-correlation functionals, resolution-of-identity (RI) approximation for ERIs, DIIS convergence acceleration, plane-wave pseudopotential (PW-PP), linear-scaling DFT. | J8: QM9 — DFT-computed properties of 134k organic molecules (https://doi.org/10.6084/m9.figshare.978904); ANI-1ccx — CCSD(T)-level energies for diverse organic molecules (https://github.com/isayev/ANI1ccx_dataset); PubChemQC — DFT calculations for ~3M PubChem molecules (http://pubchemqc.riken.jp); CSD — Cambridge Structural Database for crystal structures (https://www.ccdc.cam.ac.uk). | K8: TeraChem (https://www.petachem.com) — GPU-native DFT, commercial but widely cited; PySCF (https://github.com/pyscf/pyscf) — pure Python quantum chemistry with GPU4PySCF extension; CP2K (https://github.com/cp2k/cp2k) — GPU-accelerated mixed Gaussian/plane-wave DFT; NWChem (https://github.com/nwchemgit/nwchem) — parallel quantum chemistry with GPU-accelerated modules. | L8: Custom CUDA kernels for ERI computation (two-electron integrals in shared memory); cuBLAS for matrix diagonalization; cuFFT for plane-wave FFT; warp-level parallelism over shell pairs. --
A9: 8 | B9: 1 | C9: Drug Discovery & Molecular Design | D9: 1.8 | E9: Semi-Empirical & Tight-Binding Quantum Methods | F9: Beginner | G9: Established | H9: Semi-empirical methods (PM7, GFN2-xTB) approximate quantum mechanics at 100–10000× lower cost than DFT by parameterizing integral expressions with empirical data. They bridge the gap between force fields and full DFT, enabling geometry optimization and reactivity screening of drug-like molecules at scale. GPU implementations parallelize the sparse Hamiltonian construction and diagonalization over molecule batches — thousands of small molecules can be optimized simultaneously on one GPU. XTB is critical for conformer ranking, tautomer enumeration, and QM-based ADMET calculation in modern drug discovery pipelines. | I9: MNDO/AM1/PM6/PM7 Hamiltonians, GFN1/GFN2-xTB (extended tight-binding), DFTB+ (density functional tight binding), diagonalization via cuSOLVER, GPU-batched molecular calculations. | J9: ANI-1 — 20M DFT energy calculations on 57k molecules (https://github.com/isayev/ANI1); QM9 (https://doi.org/10.6084/m9.figshare.978904); GMTKN55 — benchmark thermochemistry and kinetics set (https://www.chemie.uni-bonn.de/grimme/de/software/gmtkn); COMPAS — computational database of polycyclic aromatic systems (verify URL). | K9: xtb (https://github.com/grimme-lab/xtb) — GFN2-xTB reference implementation (CPU-only but used as GPU backend reference); DFTB+ (https://github.com/dftbplus/dftbplus) — GPU-accelerated DFTB via ELPA library; GFN-FF / xTB-IFF (https://github.com/grimme-lab) — force field from tight binding; TBLite (https://github.com/tblite/tblite) — lightweight tight-binding library. | L9: cuSOLVER for batch matrix diagonalization; cuBLAS for Hamiltonian density-matrix products; custom CUDA kernels for two-center integral batches; stream concurrency to overlap compute and data transfer for molecule batches. --
A10: 9 | B10: 1 | C10: Drug Discovery & Molecular Design | D10: 1.9 | E10: ML Interatomic Potentials (Neural Network Potentials) | F10: Beginner | G10: Established | H10: Neural network potentials (NNPs) learn the potential energy surface from ab initio data, reproducing DFT accuracy at near-classical MD speed. Architectures range from atom-centered symmetry functions (ANI) to equivariant message-passing networks (NequIP, MACE, SchNet). GPU acceleration is essential: each forward pass involves neighborhood construction, message passing over all atomic pairs within a cutoff, and backpropagation for forces. On an A100, a 500-atom protein+ligand system runs at ~10 ns/day — 1000× slower than classical FF but 100× faster than DFT, enabling reactive drug-target simulations previously impossible. | I10: Atom-centered symmetry functions (ACSF/BEHLER), equivariant neural networks (E(3)-equivariant / SE(3)), message-passing neural networks (MPNN/SchNet/DimeNet), MACE (multi-ACE), NequIP, neural achitecture via PyTorch Geometric. | J10: ANI-1ccx — CCSD(T) energies on 500k conformers of drug-like molecules (https://github.com/isayev/ANI1ccx_dataset); SPICE — quantum chemistry dataset for ML potentials covering drug-like molecules and proteins (https://github.com/openmm/spice-dataset); rMD17 — revised MD17 benchmark (https://figshare.com/articles/dataset/Revised_MD17_dataset_rMD17_/12672038); OE62 — 62k organic molecules with DFT energetics (verify URL). | K10: TorchANI (https://github.com/aiqm/torchani) — PyTorch ANI NNP with CUDA acceleration and OpenMM integration; TorchMD-Net (https://github.com/torchmd/torchmd-net) — equivariant NNPs with GPU-optimized neighbor list; MACE (https://github.com/ACEsuit/mace) — fast equivariant NNP with GPU kernels; NequIP (https://github.com/mir-group/nequip) — E(3)-equivariant network for accurate NNPs. | L10: PyTorch CUDA autograd for force computation via backpropagation; custom CUDA kernels for neighbor list construction with periodic boundaries; torch.compile/TorchScript for inference optimization; multi-GPU via DDP for training. --
A11: 10 | B11: 1 | C11: Drug Discovery & Molecular Design | D11: 1.10 | E11: De Novo Generative Molecular Design | F11: Intermediate | G11: Active R&D | H11: Generative models learn the distribution of drug-like molecules and sample novel structures optimized for multiple properties (potency, selectivity, ADMET, synthesizability). GPU training is mandatory: large transformer/RNN/diffusion models over SMILES strings or 3D molecular graphs require days on multi-GPU nodes. At inference, reinforcement learning (RL) fine-tuning generates thousands of candidate molecules per GPU-second, enabling goal-directed optimization. REINVENT4 combines RL with curriculum learning on SMILES; diffusion-based methods (DiffSBDD, TargetDiff) generate molecules directly in 3D protein binding pockets. | I11: Variational autoencoders (VAE), transformer language models on SMILES/SELFIES, graph generative models, denoising diffusion probabilistic models (DDPM), reinforcement learning with REINFORCE/PPO, scoring functions (docking, QED, SA score). | J11: ChEMBL — 2M+ bioactive molecules (https://www.ebi.ac.uk/chembl/); ZINC20 — 1.4B purchasable compounds (https://zinc20.docking.org); GuacaMol benchmark — distribution learning and goal-directed generation benchmarks (https://github.com/BenevolentAI/guacamol); MOSES — molecular generation benchmarks (https://github.com/molecularsets/moses). | K11: REINVENT4 (https://github.com/MolecularAI/REINVENT4) — production SMILES generative model with RL, Apache 2.0 license; DiffSBDD (https://github.com/arneschneuing/DiffSBDD) — 3D structure-based diffusion design; DiffDock (https://github.com/gcorso/DiffDock) — diffusion model for pose generation used in SBDD pipelines; DeepChem (https://github.com/deepchem/deepchem) — broad ML drug discovery toolkit including generative models. | L11: cuDNN for transformer/RNN layers; custom CUDA scatter/gather for molecular graph message passing; multi-GPU DDP training; FP16 mixed precision via torch.amp; GPU-batched scoring function evaluation during RL rollouts. --
A12: 11 | B12: 1 | C12: Drug Discovery & Molecular Design | D12: 1.11 | E12: QSAR / Property Prediction | F12: Beginner | G12: Established | H12: Quantitative structure-activity relationship (QSAR) models predict biological activity from molecular descriptors or learned representations. Modern approaches use message-passing neural networks (MPNNs) over molecular graphs, enabling GPU-batched training on millions of labeled datapoints. The bottleneck shifts from feature computation to batch normalization and message aggregation over irregular graph structures — handled by PyTorch Geometric or DGL with CUDA backends. GPU-accelerated QSAR models at pharmaceutical companies screen hundreds of millions of virtual compounds per hour for ADMET and activity filters. | I12: Directed message-passing (D-MPNN / Chemprop), graph convolutional networks (GCN), graph attention networks (GAT), transformer on molecular graphs (Uni-Mol), random forest / XGBoost on Morgan fingerprints, uncertainty quantification (ensemble, MCDropout). | J12: MoleculeNet — curated ML benchmark for 17+ molecular datasets (https://moleculenet.org); ChEMBL bioactivity data (https://www.ebi.ac.uk/chembl/); TDC (Therapeutics Data Commons) — 66 tasks for drug discovery ML (https://tdcommons.ai); PCBA (PubChem BioAssay) — 128 bioassays on 440k compounds (https://moleculenet.org). | K12: Chemprop (https://github.com/chemprop/chemprop) — D-MPNN for molecular property prediction, GPU training; Uni-Mol (https://github.com/deepmodeling/Uni-Mol) — 3D molecular transformer pre-trained on 209M conformers; DeepChem (https://github.com/deepchem/deepchem) — broad GPU-accelerated ML chemistry toolkit; DGL-LifeSci (https://github.com/awslabs/dgl-lifesci) — graph neural networks for life science on GPU. | L12: PyTorch Geometric CUDA sparse tensor ops for graph batching; cuDNN for feedforward layers; FP16 mixed precision; GPU-accelerated descriptor generation via RDKit CUDA extensions (verify URL). --
A13: 12 | B13: 1 | C13: Drug Discovery & Molecular Design | D13: 1.12 | E13: Molecular Fingerprint Similarity Search | F13: Beginner | G13: Established | H13: Tanimoto similarity between Morgan/ECFP bit-vectors is the standard metric for chemical similarity searching. Brute-force comparison of a query against a library of 100M compounds requires 10^10 bit-AND/popcount operations — ideally suited for GPU SIMD. Each 2048-bit fingerprint fits in 32 uint64 words; a GPU thread evaluates one query-vs-library pair in ~5 ns. Schrodinger's gpusimilarity loads an entire library into GPU memory and achieves sub-second retrieval on billion-compound libraries. The GPU pattern is embarrassingly data-parallel with a final topK reduction. | I13: Tanimoto coefficient (Jaccard on bit-vectors), Morgan/ECFP fingerprints (radius 2–3), TopK reduction, LSH-based approximate search, Faiss IVF for high-dimensional vectors. | J13: ChEMBL (https://www.ebi.ac.uk/chembl/); ZINC20 (https://zinc20.docking.org); PubChem Compound — 115M+ compounds (https://pubchem.ncbi.nlm.nih.gov); Enamine REAL (https://enamine.net). | K13: gpusimilarity (https://github.com/schrodinger/gpusimilarity) — CUDA/Thrust brute-force fingerprint search; FPSim2 (https://github.com/chembl/FPSim2) — fast similarity search using PyTables and GPU-accelerated popcount; RDKit (https://github.com/rdkit/rdkit) — cheminformatics toolkit with Morgan fingerprint generation; Faiss (https://github.com/facebookresearch/faiss) — GPU-accelerated ANN search applicable to molecular embeddings. | L13: Thrust device_vector for library storage; custom CUDA kernels with __popcll() for bit-count; warp-shuffle reduction for partial Tanimoto sums; GPU topK using cub::DeviceRadixSort; texture memory for fingerprint cache. --
... A302: 301 | B302: 14 | C302: Emerging, Theoretical & Grand-Challenge Frontiers | D302: 14.16 | E302: GPU Cellular Automata for Tissue Morphogenesis | F302: Intermediate | G302: Active R&D | H302: Lattice-Gas Cellular Automata (LGCA) and Cellular Automata (CA) models simulate tumor invasion, wound healing, and developmental tissue patterning at the cell scale on million-element grids. Every lattice site updates in parallel based on local neighborhood rules — a perfectly SIMT workload. GPU CA for tumor growth integrates nutrient diffusion (CUDA stencil), cell-cycle progression, and proliferation/death rules, enabling parameter sweeps over invasion phenotypes that would be intractable on CPU. Hybrid CA-PDE models couple discrete cell lattice (CUDA) with continuous nutrient/oxygen fields (CUDA finite difference). | I302: Lattice-Gas CA (LGCA) for cell migration, Cellular Automaton tumor model (Kansal-Torquato), Go-or-Grow phenotype switching, reaction-diffusion PDE for morphogens, Potts model for cell sorting, hybrid CA-FEM multiscale coupling. | J302: CancerOrganoid Drug Response Images (verify URL via Hubrecht); TCGA pathology slides for CA calibration (https://portal.gdc.cancer.gov/); CellMorph — time-lapse cell migration datasets (verify URL); Wound-Healing Assay Image Repository (verify URL via protocols.io). | K302: PhysiCell (https://github.com/MathCancer/PhysiCell) — GPU-parallelized 3D agent-based tissue simulator; CompuCell3D (https://compucell3d.org/) — multi-algorithm tissue simulator with GPU support; CancerSim (https://github.com/joancalvente/cancersim) — GPU CA tumor growth code; Morpheus (https://morpheus.gitlab.io/) — spatial cell model simulation with GPU backend. | L302: CUDA 2D/3D stencil kernels for CA lattice update, cuRAND for stochastic cell-fate decisions, Thrust for parallel phenotype census; pattern: N×N×N GPU lattice → one CUDA thread per lattice site → local rule evaluation → stochastic update → reaction-diffusion field update → time-step advance → GPU-rendered morphology export.

Sheet By Domain
A1: Domain | B1: Total | C1: 🟢 Beginner | D1: 🟡 Intermediate | E1: 🔴 Advanced | F1: Established | G1: Active R&D | H1: Frontier/Theoretical
A2: Drug Discovery & Molecular Design | B2: =COUNTIF(Projects!$C:$C,"Drug Discovery & Molecular Design") -> 35 | C2: =COUNTIFS(Projects!$C:$C,"Drug Discovery & Molecular Design",Projects!$F:$F,"Beginner") -> 18 | D2: =COUNTIFS(Projects!$C:$C,"Drug Discovery & Molecular Design",Projects!$F:$F,"Intermediate") -> 16 | E2: =COUNTIFS(Projects!$C:$C,"Drug Discovery & Molecular Design",Projects!$F:$F,"Advanced") -> 1 | F2: =COUNTIFS(Projects!$C:$C,"Drug Discovery & Molecular Design",Projects!$G:$G,"Established") -> 18 | G2: =COUNTIFS(Projects!$C:$C,"Drug Discovery & Molecular Design",Projects!$G:$G,"Active R&D") -> 16 | H2: =COUNTIFS(Projects!$C:$C,"Drug Discovery & Molecular Design",Projects!$G:$G,"Frontier/Theoretical") -> 1
A3: Structural Biology & Protein Science | B3: =COUNTIF(Projects!$C:$C,"Structural Biology & Protein Science") -> 35 | C3: =COUNTIFS(Projects!$C:$C,"Structural Biology & Protein Science",Projects!$F:$F,"Beginner") -> 10 | D3: =COUNTIFS(Projects!$C:$C,"Structural Biology & Protein Science",Projects!$F:$F,"Intermediate") -> 21 | E3: =COUNTIFS(Projects!$C:$C,"Structural Biology & Protein Science",Projects!$F:$F,"Advanced") -> 4 | F3: =COUNTIFS(Projects!$C:$C,"Structural Biology & Protein Science",Projects!$G:$G,"Established") -> 10 | G3: =COUNTIFS(Projects!$C:$C,"Structural Biology & Protein Science",Projects!$G:$G,"Active R&D") -> 21 | H3: =COUNTIFS(Projects!$C:$C,"Structural Biology & Protein Science",Projects!$G:$G,"Frontier/Theoretical") -> 4
A4: Genomics, Sequencing & Bioinformatics | B4: =COUNTIF(Projects!$C:$C,"Genomics, Sequencing & Bioinformatics") -> 30 | C4: =COUNTIFS(Projects!$C:$C,"Genomics, Sequencing & Bioinformatics",Projects!$F:$F,"Beginner") -> 8 | D4: =COUNTIFS(Projects!$C:$C,"Genomics, Sequencing & Bioinformatics",Projects!$F:$F,"Intermediate") -> 22 | E4: =COUNTIFS(Projects!$C:$C,"Genomics, Sequencing & Bioinformatics",Projects!$F:$F,"Advanced") -> 0 | F4: =COUNTIFS(Projects!$C:$C,"Genomics, Sequencing & Bioinformatics",Projects!$G:$G,"Established") -> 8 | G4: =COUNTIFS(Projects!$C:$C,"Genomics, Sequencing & Bioinformatics",Projects!$G:$G,"Active R&D") -> 22 | H4: =COUNTIFS(Projects!$C:$C,"Genomics, Sequencing & Bioinformatics",Projects!$G:$G,"Frontier/Theoretical") -> 0
A5: Medical Imaging & Image Reconstruction | B5: =COUNTIF(Projects!$C:$C,"Medical Imaging & Image Reconstruction") -> 33 | C5: =COUNTIFS(Projects!$C:$C,"Medical Imaging & Image Reconstruction",Projects!$F:$F,"Beginner") -> 7 | D5: =COUNTIFS(Projects!$C:$C,"Medical Imaging & Image Reconstruction",Projects!$F:$F,"Intermediate") -> 26 | E5: =COUNTIFS(Projects!$C:$C,"Medical Imaging & Image Reconstruction",Projects!$F:$F,"Advanced") -> 0 | F5: =COUNTIFS(Projects!$C:$C,"Medical Imaging & Image Reconstruction",Projects!$G:$G,"Established") -> 7 | G5: =COUNTIFS(Projects!$C:$C,"Medical Imaging & Image Reconstruction",Projects!$G:$G,"Active R&D") -> 26 | H5: =COUNTIFS(Projects!$C:$C,"Medical Imaging & Image Reconstruction",Projects!$G:$G,"Frontier/Theoretical") -> 0
A6: Radiation Therapy & Medical Physics | B6: =COUNTIF(Projects!$C:$C,"Radiation Therapy & Medical Physics") -> 15 | C6: =COUNTIFS(Projects!$C:$C,"Radiation Therapy & Medical Physics",Projects!$F:$F,"Beginner") -> 4 | D6: =COUNTIFS(Projects!$C:$C,"Radiation Therapy & Medical Physics",Projects!$F:$F,"Intermediate") -> 6 | E6: =COUNTIFS(Projects!$C:$C,"Radiation Therapy & Medical Physics",Projects!$F:$F,"Advanced") -> 5 | F6: =COUNTIFS(Projects!$C:$C,"Radiation Therapy & Medical Physics",Projects!$G:$G,"Established") -> 4 | G6: =COUNTIFS(Projects!$C:$C,"Radiation Therapy & Medical Physics",Projects!$G:$G,"Active R&D") -> 6 | H6: =COUNTIFS(Projects!$C:$C,"Radiation Therapy & Medical Physics",Projects!$G:$G,"Frontier/Theoretical") -> 5
A7: Computational Physiology & Systems Biology | B7: =COUNTIF(Projects!$C:$C,"Computational Physiology & Systems Biology") -> 27 | C7: =COUNTIFS(Projects!$C:$C,"Computational Physiology & Systems Biology",Projects!$F:$F,"Beginner") -> 5 | D7: =COUNTIFS(Projects!$C:$C,"Computational Physiology & Systems Biology",Projects!$F:$F,"Intermediate") -> 22 | E7: =COUNTIFS(Projects!$C:$C,"Computational Physiology & Systems Biology",Projects!$F:$F,"Advanced") -> 0 | F7: =COUNTIFS(Projects!$C:$C,"Computational Physiology & Systems Biology",Projects!$G:$G,"Established") -> 5 | G7: =COUNTIFS(Projects!$C:$C,"Computational Physiology & Systems Biology",Projects!$G:$G,"Active R&D") -> 22 | H7: =COUNTIFS(Projects!$C:$C,"Computational Physiology & Systems Biology",Projects!$G:$G,"Frontier/Theoretical") -> 0
A8: Medical AI & Clinical Deep Learning | B8: =COUNTIF(Projects!$C:$C,"Medical AI & Clinical Deep Learning") -> 19 | C8: =COUNTIFS(Projects!$C:$C,"Medical AI & Clinical Deep Learning",Projects!$F:$F,"Beginner") -> 3 | D8: =COUNTIFS(Projects!$C:$C,"Medical AI & Clinical Deep Learning",Projects!$F:$F,"Intermediate") -> 14 | E8: =COUNTIFS(Projects!$C:$C,"Medical AI & Clinical Deep Learning",Projects!$F:$F,"Advanced") -> 2 | F8: =COUNTIFS(Projects!$C:$C,"Medical AI & Clinical Deep Learning",Projects!$G:$G,"Established") -> 3 | G8: =COUNTIFS(Projects!$C:$C,"Medical AI & Clinical Deep Learning",Projects!$G:$G,"Active R&D") -> 14 | H8: =COUNTIFS(Projects!$C:$C,"Medical AI & Clinical Deep Learning",Projects!$G:$G,"Frontier/Theoretical") -> 2
A9: Neuroscience & Brain-Computer Interfaces | B9: =COUNTIF(Projects!$C:$C,"Neuroscience & Brain-Computer Interfaces") -> 16 | C9: =COUNTIFS(Projects!$C:$C,"Neuroscience & Brain-Computer Interfaces",Projects!$F:$F,"Beginner") -> 3 | D9: =COUNTIFS(Projects!$C:$C,"Neuroscience & Brain-Computer Interfaces",Projects!$F:$F,"Intermediate") -> 10 | E9: =COUNTIFS(Projects!$C:$C,"Neuroscience & Brain-Computer Interfaces",Projects!$F:$F,"Advanced") -> 3 | F9: =COUNTIFS(Projects!$C:$C,"Neuroscience & Brain-Computer Interfaces",Projects!$G:$G,"Established") -> 3 | G9: =COUNTIFS(Projects!$C:$C,"Neuroscience & Brain-Computer Interfaces",Projects!$G:$G,"Active R&D") -> 10 | H9: =COUNTIFS(Projects!$C:$C,"Neuroscience & Brain-Computer Interfaces",Projects!$G:$G,"Frontier/Theoretical") -> 3
A10: Epidemiology & Public Health | B10: =COUNTIF(Projects!$C:$C,"Epidemiology & Public Health") -> 10 | C10: =COUNTIFS(Projects!$C:$C,"Epidemiology & Public Health",Projects!$F:$F,"Beginner") -> 0 | D10: =COUNTIFS(Projects!$C:$C,"Epidemiology & Public Health",Projects!$F:$F,"Intermediate") -> 9 | E10: =COUNTIFS(Projects!$C:$C,"Epidemiology & Public Health",Projects!$F:$F,"Advanced") -> 1 | F10: =COUNTIFS(Projects!$C:$C,"Epidemiology & Public Health",Projects!$G:$G,"Established") -> 0 | G10: =COUNTIFS(Projects!$C:$C,"Epidemiology & Public Health",Projects!$G:$G,"Active R&D") -> 9 | H10: =COUNTIFS(Projects!$C:$C,"Epidemiology & Public Health",Projects!$G:$G,"Frontier/Theoretical") -> 1
A11: Biomechanics, Biomedical Devices & Surgery | B11: =COUNTIF(Projects!$C:$C,"Biomechanics, Biomedical Devices & Surgery") -> 17 | C11: =COUNTIFS(Projects!$C:$C,"Biomechanics, Biomedical Devices & Surgery",Projects!$F:$F,"Beginner") -> 3 | D11: =COUNTIFS(Projects!$C:$C,"Biomechanics, Biomedical Devices & Surgery",Projects!$F:$F,"Intermediate") -> 14 | E11: =COUNTIFS(Projects!$C:$C,"Biomechanics, Biomedical Devices & Surgery",Projects!$F:$F,"Advanced") -> 0 | F11: =COUNTIFS(Projects!$C:$C,"Biomechanics, Biomedical Devices & Surgery",Projects!$G:$G,"Established") -> 3 | G11: =COUNTIFS(Projects!$C:$C,"Biomechanics, Biomedical Devices & Surgery",Projects!$G:$G,"Active R&D") -> 14 | H11: =COUNTIFS(Projects!$C:$C,"Biomechanics, Biomedical Devices & Surgery",Projects!$G:$G,"Frontier/Theoretical") -> 0
A12: Biotechnology, Bioprocess & Synthetic Biology | B12: =COUNTIF(Projects!$C:$C,"Biotechnology, Bioprocess & Synthetic Biology") -> 12 | C12: =COUNTIFS(Projects!$C:$C,"Biotechnology, Bioprocess & Synthetic Biology",Projects!$F:$F,"Beginner") -> 0 | D12: =COUNTIFS(Projects!$C:$C,"Biotechnology, Bioprocess & Synthetic Biology",Projects!$F:$F,"Intermediate") -> 12 | E12: =COUNTIFS(Projects!$C:$C,"Biotechnology, Bioprocess & Synthetic Biology",Projects!$F:$F,"Advanced") -> 0 | F12: =COUNTIFS(Projects!$C:$C,"Biotechnology, Bioprocess & Synthetic Biology",Projects!$G:$G,"Established") -> 0 | G12: =COUNTIFS(Projects!$C:$C,"Biotechnology, Bioprocess & Synthetic Biology",Projects!$G:$G,"Active R&D") -> 12 | H12: =COUNTIFS(Projects!$C:$C,"Biotechnology, Bioprocess & Synthetic Biology",Projects!$G:$G,"Frontier/Theoretical") -> 0
A13: Analytical & Omics Data Processing | B13: =COUNTIF(Projects!$C:$C,"Analytical & Omics Data Processing") -> 17 | C13: =COUNTIFS(Projects!$C:$C,"Analytical & Omics Data Processing",Projects!$F:$F,"Beginner") -> 4 | D13: =COUNTIFS(Projects!$C:$C,"Analytical & Omics Data Processing",Projects!$F:$F,"Intermediate") -> 13 | E13: =COUNTIFS(Projects!$C:$C,"Analytical & Omics Data Processing",Projects!$F:$F,"Advanced") -> 0 | F13: =COUNTIFS(Projects!$C:$C,"Analytical & Omics Data Processing",Projects!$G:$G,"Established") -> 4 | G13: =COUNTIFS(Projects!$C:$C,"Analytical & Omics Data Processing",Projects!$G:$G,"Active R&D") -> 13 | H13: =COUNTIFS(Projects!$C:$C,"Analytical & Omics Data Processing",Projects!$G:$G,"Frontier/Theoretical") -> 0
A14: Pharmacology & Clinical Quantitative Modeling | B14: =COUNTIF(Projects!$C:$C,"Pharmacology & Clinical Quantitative Modeling") -> 19 | C14: =COUNTIFS(Projects!$C:$C,"Pharmacology & Clinical Quantitative Modeling",Projects!$F:$F,"Beginner") -> 2 | D14: =COUNTIFS(Projects!$C:$C,"Pharmacology & Clinical Quantitative Modeling",Projects!$F:$F,"Intermediate") -> 13 | E14: =COUNTIFS(Projects!$C:$C,"Pharmacology & Clinical Quantitative Modeling",Projects!$F:$F,"Advanced") -> 4 | F14: =COUNTIFS(Projects!$C:$C,"Pharmacology & Clinical Quantitative Modeling",Projects!$G:$G,"Established") -> 2 | G14: =COUNTIFS(Projects!$C:$C,"Pharmacology & Clinical Quantitative Modeling",Projects!$G:$G,"Active R&D") -> 13 | H14: =COUNTIFS(Projects!$C:$C,"Pharmacology & Clinical Quantitative Modeling",Projects!$G:$G,"Frontier/Theoretical") -> 4
A15: Emerging, Theoretical & Grand-Challenge Frontiers | B15: =COUNTIF(Projects!$C:$C,"Emerging, Theoretical & Grand-Challenge Frontiers") -> 16 | C15: =COUNTIFS(Projects!$C:$C,"Emerging, Theoretical & Grand-Challenge Frontiers",Projects!$F:$F,"Beginner") -> 0 | D15: =COUNTIFS(Projects!$C:$C,"Emerging, Theoretical & Grand-Challenge Frontiers",Projects!$F:$F,"Intermediate") -> 8 | E15: =COUNTIFS(Projects!$C:$C,"Emerging, Theoretical & Grand-Challenge Frontiers",Projects!$F:$F,"Advanced") -> 8 | F15: =COUNTIFS(Projects!$C:$C,"Emerging, Theoretical & Grand-Challenge Frontiers",Projects!$G:$G,"Established") -> 0 | G15: =COUNTIFS(Projects!$C:$C,"Emerging, Theoretical & Grand-Challenge Frontiers",Projects!$G:$G,"Active R&D") -> 8 | H15: =COUNTIFS(Projects!$C:$C,"Emerging, Theoretical & Grand-Challenge Frontiers",Projects!$G:$G,"Frontier/Theoretical") -> 8
A16: TOTAL | B16: =SUM(B2:B15) -> 301 | C16: =SUM(C2:C15) -> 67 | D16: =SUM(D2:D15) -> 206 | E16: =SUM(E2:E15) -> 28 | F16: =SUM(F2:F15) -> 67 | G16: =SUM(G2:G15) -> 206 | H16: =SUM(H2:H15) -> 28
